montyalex-0.1.4.dist-info/METADATA
montyalex-0.1.4.dist-info/WHEEL
montyalex-0.1.4.dist-info/entry_points.txt
montyalex/__init__.py
montyalex/_mtax.py
montyalex/_settings.py
montyalex/app.py
montyalex/cache_tools/__init__.py
montyalex/cache_tools/cache_app.py
montyalex/cache_tools/cache_helpers.py
montyalex/cache_tools/mtax_cache.py
montyalex/cache_tools/timecache_app.py
montyalex/cache_tools/zonecache_app.py
montyalex/console_tools/__init__.py
montyalex/directory_tools/__init__.py
montyalex/directory_tools/datedirs.py
montyalex/directory_tools/helpdirs.py
montyalex/directory_tools/simpledirs.py
montyalex/fs_tools/__init__.py
montyalex/fs_tools/path.py
montyalex/fs_tools/paths.py
montyalex/fs_tools/system.py
montyalex/future_tools/__init__.py
montyalex/future_tools/by_2024_11_27.py
montyalex/future_tools/by_2024_12_25.py
montyalex/lang_tools/__init__.py
montyalex/lang_tools/lang2lang.py
montyalex/object_tools/__init__.py
montyalex/object_tools/enumeration.py
montyalex/object_tools/exceptions.py
montyalex/object_tools/pickling.py
montyalex/object_tools/singleton.py
montyalex/time_tools/__init__.py
montyalex/time_tools/mtax_time.py
montyalex/time_tools/timing.py
montyalex/tree_tools/__init__.py
montyalex/tree_tools/presets.py
montyalex/tree_tools/tree_app.py
montyalex/tree_tools/treeid.py
montyalex/tree_tools/void.py
montyalex/typer_helpers/__init__.py
montyalex/typer_helpers/directories.py
montyalex/typer_helpers/init_objects.py
montyalex/typer_helpers/initialization.py
montyalex/typer_helpers/mtax.py
montyalex/typer_helpers/uo_delete.py
montyalex/typer_helpers/uo_init.py
montyalex/typer_helpers/uo_inspect.py
montyalex/typer_tools/__init__.py
montyalex/typing_tools/__init__.py
montyalex/uo_tools/__init__.py
montyalex/uo_tools/_template.py
montyalex/uo_tools/_useroptions.py
montyalex/uo_tools/json_schema_template.py
montyalex/uo_tools/json_template.py
montyalex/uo_tools/mpck_template.py
montyalex/uo_tools/toml_template.py
montyalex/uo_tools/yaml_template.py
montyalex/us_tools/__init__.py
montyalex/us_tools/__setting_repr_example.txt
montyalex/us_tools/_actions.py
montyalex-0.1.4.dist-info/RECORD
